api_simulator/__init__.py
api_simulator/app.py
api_simulator/cli.py
api_simulator/openapi.py
api_simulator/schema.py
api_simulator/templates.py
api_simulator-0.3.0.dist-info/licenses/LICENSE
api_simulator-0.3.0.dist-info/METADATA
api_simulator-0.3.0.dist-info/WHEEL
api_simulator-0.3.0.dist-info/entry_points.txt
api_simulator-0.3.0.dist-info/top_level.txt
api_simulator-0.3.0.dist-info/RECORD
