Metadata-Version: 2.4
Name: api-simulator
Version: 0.3.0
Summary: Multi-protocol API mocking made simple - REST, GraphQL, WebSocket, UDP from a single JSON config
Author-email: API Simulator Team <support@example.com>
License: MIT
Project-URL: Homepage, https://github.com/yourusername/api-simulator
Project-URL: Documentation, https://github.com/yourusername/api-simulator#documentation
Project-URL: Repository, https://github.com/yourusername/api-simulator.git
Project-URL: Issues, https://github.com/yourusername/api-simulator/issues
Keywords: api,mock,simulator,rest,graphql,websocket,udp,testing,development
Classifier: Development Status :: 4 - Beta
Classifier: Intended Audience :: Developers
Classifier: Topic :: Software Development :: Testing
Classifier: Topic :: Software Development :: Testing :: Mocking
Classifier: License :: OSI Approved :: MIT License
Classifier: Programming Language :: Python :: 3
Classifier: Programming Language :: Python :: 3.9
Classifier: Programming Language :: Python :: 3.10
Classifier: Programming Language :: Python :: 3.11
Classifier: Programming Language :: Python :: 3.12
Classifier: Operating System :: OS Independent
Requires-Python: >=3.9
License-File: LICENSE
Requires-Dist: fastapi>=0.110
Requires-Dist: uvicorn[standard]>=0.24
Requires-Dist: websockets>=12.0
Requires-Dist: msgpack>=1.0
Requires-Dist: pydantic>=2.6
Requires-Dist: starlette>=0.37
Requires-Dist: jsonschema>=4.22
Provides-Extra: test
Requires-Dist: pytest>=7.0; extra == "test"
Requires-Dist: pytest-asyncio>=0.21; extra == "test"
Requires-Dist: httpx>=0.24; extra == "test"
Dynamic: license-file
